mcloud/__init__.py
mcloud/auth.py
mcloud/client.py
mcloud/config.py
mcloud/constants.py
mcloud/errors.py
mcloud/logger.py
mcloud/main.py
mcloud/prompter.py
mcloud/publish.py
mcloud/generated/__init__.py
mcloud/generated/client.py
mcloud/generated/core/__init__.py
mcloud/generated/core/api_error.py
mcloud/generated/core/datetime_utils.py
mcloud/generated/core/jsonable_encoder.py
mcloud/generated/core/remove_none_from_headers.py
mcloud/generated/resources/__init__.py
mcloud/generated/resources/marimo_v_1/__init__.py
mcloud/generated/resources/marimo_v_1/client.py
mcloud/generated/resources/marimo_v_1/errors/__init__.py
mcloud/generated/resources/marimo_v_1/errors/application_not_found_error.py
mcloud/generated/resources/marimo_v_1/errors/application_slug_already_exists_error.py
mcloud/generated/resources/marimo_v_1/errors/expired_token_error.py
mcloud/generated/resources/marimo_v_1/errors/missing_fields_error.py
mcloud/generated/resources/marimo_v_1/errors/organization_not_found_error.py
mcloud/generated/resources/marimo_v_1/errors/permission_denied_error.py
mcloud/generated/resources/marimo_v_1/types/__init__.py
mcloud/generated/resources/marimo_v_1/types/application.py
mcloud/generated/resources/marimo_v_1/types/application_id.py
mcloud/generated/resources/marimo_v_1/types/application_slug.py
mcloud/generated/resources/marimo_v_1/types/create_application_request.py
mcloud/generated/resources/marimo_v_1/types/create_upload_url_response.py
mcloud/generated/resources/marimo_v_1/types/deployment.py
mcloud/generated/resources/marimo_v_1/types/deployment_id.py
mcloud/generated/resources/marimo_v_1/types/organization.py
mcloud/generated/resources/marimo_v_1/types/organization_id.py
mcloud/generated/resources/marimo_v_1/types/organization_slug.py
mcloud/resources/resources.py
marimo_cloud-0.2.1.dist-info/METADATA
marimo_cloud-0.2.1.dist-info/WHEEL
marimo_cloud-0.2.1.dist-info/entry_points.txt
marimo_cloud-0.2.1.dist-info/top_level.txt
marimo_cloud-0.2.1.dist-info/RECORD
