Metadata-Version: 2.1
Name: marimo-cloud
Version: 0.2.1
Project-URL: homepage, https://marimo.io
Classifier: Programming Language :: Python :: 3
Requires-Python: >=3.8
Requires-Dist: typer ~=0.9.0
Requires-Dist: rich ~=13.7.0
Requires-Dist: inquirer ~=3.2.3
Requires-Dist: httpx ~=0.26.0
Requires-Dist: toml ~=0.10.2
Requires-Dist: pydantic ~=1.10.14
Provides-Extra: dev
Requires-Dist: click <8.1.8 ; extra == 'dev'
Requires-Dist: black ~=24.1.1 ; extra == 'dev'
Requires-Dist: build ~=1.0.3 ; extra == 'dev'
Requires-Dist: pytest ~=8.0.0 ; extra == 'dev'
Requires-Dist: mypy ~=1.8.0 ; extra == 'dev'
Requires-Dist: ruff ~=0.2.0 ; extra == 'dev'
